peru/VERSION
peru/__init__.py
peru/__main__.py
peru/async_exit_stack.py
peru/async_helpers.py
peru/cache.py
peru/compat.py
peru/display.py
peru/edit_yaml.py
peru/error.py
peru/glob.py
peru/imports.py
peru/keyval.py
peru/main.py
peru/merge.py
peru/module.py
peru/parser.py
peru/plugin.py
peru/rule.py
peru/runtime.py
peru/scope.py
peru/docopt/__init__.py
peru/docopt/_version.py
peru/resources/plugins/bat/bat_plugin.bat
peru/resources/plugins/bat/plugin.yaml
peru/resources/plugins/cp/cp_plugin.py
peru/resources/plugins/cp/plugin.yaml
peru/resources/plugins/curl/curl_plugin.py
peru/resources/plugins/curl/plugin.yaml
peru/resources/plugins/empty/empty_plugin.py
peru/resources/plugins/empty/plugin.yaml
peru/resources/plugins/git/git_plugin.py
peru/resources/plugins/git/plugin.yaml
peru/resources/plugins/hg/hg_plugin.py
peru/resources/plugins/hg/plugin.yaml
peru/resources/plugins/noop_cache/noop_cache_plugin.py
peru/resources/plugins/noop_cache/plugin.yaml
peru/resources/plugins/print/plugin.yaml
peru/resources/plugins/print/print_plugin.py
peru/resources/plugins/rsync/plugin.yaml
peru/resources/plugins/rsync/rsync_plugin.sh
peru/resources/plugins/svn/plugin.yaml
peru/resources/plugins/svn/svn_plugin.py
peru-1.3.5.dist-info/METADATA
peru-1.3.5.dist-info/WHEEL
peru-1.3.5.dist-info/entry_points.txt
peru-1.3.5.dist-info/licenses/LICENSE
peru-1.3.5.dist-info/RECORD
