Metadata-Version: 2.4
Name: peru
Version: 1.3.5
Summary: A tool for fetching code
Project-URL: Repository, https://github.com/buildinspace/peru
Author-email: Jack O'Connor <oconnor663@gmail.com>, Sean Olson <olson.sean.k@gmail.com>
License-Expression: MIT
License-File: LICENSE
Requires-Python: >=3.8
Requires-Dist: pyyaml
